py3gpp/__init__.py
py3gpp/helper.py
py3gpp/nrBCH.py
py3gpp/nrBCHDecode.py
py3gpp/nrCRCDecode.py
py3gpp/nrCRCEncode.py
py3gpp/nrChannelEstimate.py
py3gpp/nrCodeBlockDesegmentLDPC.py
py3gpp/nrCodeBlockSegmentLDPC.py
py3gpp/nrDLSCHInfo.py
py3gpp/nrEqualizeMMSE.py
py3gpp/nrExtractResources.py
py3gpp/nrLDPCDecode.py
py3gpp/nrLDPCEncode.py
py3gpp/nrLayerMap.py
py3gpp/nrOFDMDemodulate.py
py3gpp/nrOFDMInfo.py
py3gpp/nrOFDMModulate.py
py3gpp/nrPBCH.py
py3gpp/nrPBCHDMRS.py
py3gpp/nrPBCHDMRSIndices.py
py3gpp/nrPBCHIndices.py
py3gpp/nrPBCHPRBS.py
py3gpp/nrPDSCH.py
py3gpp/nrPDSCHDMRS.py
py3gpp/nrPDSCHDMRSIndices.py
py3gpp/nrPDSCHDecode.py
py3gpp/nrPDSCHIndices.py
py3gpp/nrPDSCHMCSTables.py
py3gpp/nrPDSCHPTRS.py
py3gpp/nrPDSCHPTRSIndices.py
py3gpp/nrPRBS.py
py3gpp/nrPSS.py
py3gpp/nrPSSIndices.py
py3gpp/nrPathLoss.py
py3gpp/nrPolarDecode.py
py3gpp/nrPolarEncode.py
py3gpp/nrRateMatchLDPC.py
py3gpp/nrRateMatchPolar.py
py3gpp/nrRateRecoverLDPC.py
py3gpp/nrRateRecoverPolar.py
py3gpp/nrResourceGrid.py
py3gpp/nrSSS.py
py3gpp/nrSSSIndices.py
py3gpp/nrSetResources.py
py3gpp/nrSymbolDemodulate.py
py3gpp/nrSymbolModulate.py
py3gpp/nrTBS.py
py3gpp/nrTimingEstimate.py
py3gpp/nrTransformDeprecode.py
py3gpp/nrTransformPrecode.py
py3gpp/codes/__init__.py
py3gpp/codes/bg1.csv
py3gpp/codes/bg2.csv
py3gpp/configs/CommonConfig.py
py3gpp/configs/DMRSConfigBase.py
py3gpp/configs/PDSCHConfigBase.py
py3gpp/configs/PDSCHPTRSConfigBase.py
py3gpp/configs/__init__.py
py3gpp/configs/nrCarrierConfig.py
py3gpp/configs/nrNumerologyConfig.py
py3gpp/configs/nrPDSCHConfig.py
py3gpp/configs/nrPDSCHDMRSConfig.py
py3gpp/configs/nrPDSCHPTRSConfig.py
py3gpp/configs/nrPathLossConfig.py
py3gpp-0.6.0.dist-info/LICENSE
py3gpp-0.6.0.dist-info/METADATA
py3gpp-0.6.0.dist-info/WHEEL
py3gpp-0.6.0.dist-info/top_level.txt
py3gpp-0.6.0.dist-info/RECORD
