Metadata-Version: 2.1
Name: py3gpp
Version: 0.6.0
Summary: Functions for 5G NR signal processing
Author-email: Benjamin Menküc <benjamin@menkuec.de>
Project-URL: Homepage, https://github.com/catkira/py3gpp
Classifier: Development Status :: 3 - Alpha
Classifier: License :: OSI Approved :: GNU Affero General Public License v3
Classifier: Natural Language :: English
Classifier: Operating System :: OS Independent
Classifier: Programming Language :: Python
Classifier: Programming Language :: Python :: 3.8
Classifier: Programming Language :: Python :: 3.9
Classifier: Programming Language :: Python :: 3.10
Requires-Python: >=3.8
License-File: LICENSE
Requires-Dist: numpy>=1.21.0
Requires-Dist: scipy>=1.9.3
Requires-Dist: importlib_resources
